LICENSE
MANIFEST.in
NOTICE
README.rst
setup.py
kafka_dev_tools/__init__.py
kafka_dev_tools.egg-info/PKG-INFO
kafka_dev_tools.egg-info/SOURCES.txt
kafka_dev_tools.egg-info/dependency_links.txt
kafka_dev_tools.egg-info/entry_points.txt
kafka_dev_tools.egg-info/requires.txt
kafka_dev_tools.egg-info/top_level.txt
kafka_dev_tools/utils/__init__.py
kafka_dev_tools/utils/kafka_patch_review.py