Metadata-Version: 1.1
Name: kafka-dev-tools
Version: 0.0.1
Summary: Tools for Kafka developers
Home-page: https://github.com/evvers/kafka-dev-tools
Author: Evgeny Vereshchagin
Author-email: evvers@ya.ru
License: UNKNOWN
Keywords: kafka
Platform: UNKNOWN
Classifier: Development Status :: 3 - Alpha
Classifier: Intended Audience :: Developers
Classifier: License :: OSI Approved :: Apache Software License
Classifier: Programming Language :: Python :: 2
Classifier: Programming Language :: Python :: 2.7
